oilukla/__init__.py
oilukla/oilukla.py
oilukla-0.2.1.dist-info/LICENSE.txt
oilukla-0.2.1.dist-info/METADATA
oilukla-0.2.1.dist-info/WHEEL
oilukla-0.2.1.dist-info/top_level.txt
oilukla-0.2.1.dist-info/RECORD
