Metadata-Version: 2.1
Name: oilukla
Version: 0.2.1
Summary: UNKNOWN
Home-page: https://enemltd.github.io/oilukla2d/
Author: ENEMINT
Author-email: enem.sup@gmail.com
License: GPL-3.0
Keywords: game-engine 2d pyqt5
Platform: UNKNOWN
License-File: LICENSE.txt
Requires-Dist: setuptools (>=42)
Requires-Dist: wheel
Requires-Dist: pygame
Requires-Dist: keyboard
